tex2image/__init__.py
tex2image/py.typed
tex2image-0.1.6.dist-info/METADATA
tex2image-0.1.6.dist-info/WHEEL
tex2image-0.1.6.dist-info/RECORD
