Metadata-Version: 2.4
Name: tex2image
Version: 0.1.6
Summary: A simple python library for converting latex snippets to images.
Author-email: Olympiad Bot <olybot@ggim.me>
Requires-Python: >=3.9
